{
    "timeline": {
        "background": "#000000",
        "tracks": [
            {
                "clips": [
                    {
                        "asset": {
                            "type": "html",
                            "html": "<p>\"{{text}}\"</p>",
                            "css": "p { font-size: 72px; color: #FFFFFF; }",
                            "width": 750,
                            "height": 593
                        },
                        "start": 1,
                        "length": 4,
                        "offset": {
                            "x": 0.167,
                            "y": 0
                        },
                        "transition": {
                            "in": "fade"
                        }
                    }
                ]
            },
            {
                "clips": [
                    {
                        "asset": {
                            "type": "luma",
                            "src": "https://shotstack-assets.s3.amazonaws.com/luma-mattes/circle-400x400.jpg"
                        },
                        "start": 0.5,
                        "length": 4.5
                    },
                    {
                        "asset": {
                            "type": "image",
                            "src": "{{profilePictureUrl}}"
                        },
                        "start": 0.5,
                        "length": 4.5,
                        "offset": {
                            "x": -0.329,
                            "y": 0.085
                        },
                        "fit": "none",
                        "transition": {
                            "in": "fade"
                        },
                        "scale": 1
                    }
                ]
            },
            {
                "clips": [
                    {
                        "asset": {
                            "type": "html",
                            "html": "<p>{{name}}</p>",
                            "height": 75,
                            "css": "p { color: #000000; font-size: 46px; text-align: center; }",
                            "width": 360
                        },
                        "start": 0.5,
                        "length": 4.5,
                        "offset": {
                            "x": -0.332,
                            "y": -0.134
                        },
                        "transition": {
                            "in": "fade"
                        }
                    },
                    {
                        "asset": {
                            "type": "html",
                            "html": "<p>@{{username}}</p>",
                            "css": "p { color: #000000; font-size: 32px; text-align: center; }",
                            "height": 75,
                            "width": 360
                        },
                        "start": 0.5,
                        "length": 4.5,
                        "offset": {
                            "x": -0.328,
                            "y": -0.37
                        },
                        "transition": {
                            "in": "fade"
                        }
                    }
                ]
            },
            {
                "clips": [
                    {
                        "asset": {
                            "type": "html",
                            "html": "<p></p>",
                            "background": "#F5F8FA",
                            "height": 720,
                            "width": 427
                        },
                        "start": 0,
                        "length": 5,
                        "transition": {
                            "in": "carouselRightSlow"
                        },
                        "position": "left"
                    }
                ]
            }
        ]
    },
    "output": {
        "format": "mp4",
        "resolution": "hd",
        "fps": 30,
        "destinations": [
            {
                "provider": "shotstack",
                "exclude": true
            }
        ]
    }
}